adafruit_bme680.py
adafruit_circuitpython_bme680-3.7.11.dist-info/LICENSE
adafruit_circuitpython_bme680-3.7.11.dist-info/METADATA
adafruit_circuitpython_bme680-3.7.11.dist-info/WHEEL
adafruit_circuitpython_bme680-3.7.11.dist-info/top_level.txt
adafruit_circuitpython_bme680-3.7.11.dist-info/RECORD
