Metadata-Version: 2.1
Name: adafruit-circuitpython-bme680
Version: 3.7.11
Summary: CircuitPython driver for BME680 sensor over I2C
Author-email: Adafruit Industries <circuitpython@adafruit.com>
License: MIT
Project-URL: Homepage, https://github.com/adafruit/Adafruit_CircuitPython_BME680
Keywords: adafruit,blinka,circuitpython,micropython,bme680,hardware,temperature,pressure,humidity,gas
Classifier: Intended Audience :: Developers
Classifier: Topic :: Software Development :: Libraries
Classifier: Topic :: Software Development :: Embedded Systems
Classifier: Topic :: System :: Hardware
Classifier: License :: OSI Approved :: MIT License
Classifier: Programming Language :: Python :: 3
License-File: LICENSE
Requires-Dist: Adafruit-Blinka
Requires-Dist: adafruit-circuitpython-busdevice
Provides-Extra: optional
